captionbot/__init__.py
captionbot/captionbot.py
captionbot/captionbotai.pem
captionbot-0.1.5.dist-info/DESCRIPTION.rst
captionbot-0.1.5.dist-info/METADATA
captionbot-0.1.5.dist-info/RECORD
captionbot-0.1.5.dist-info/WHEEL
captionbot-0.1.5.dist-info/metadata.json
captionbot-0.1.5.dist-info/top_level.txt
