Metadata-Version: 2.0
Name: captionbot
Version: 0.1.5
Summary: Simple API wrapper for https://www.captionbot.ai/
Home-page: http://github.com/krikunts/captionbot
Author: Tatiana Krikun
Author-email: krikunts@gmail.com
License: MIT
Platform: UNKNOWN
Requires-Dist: requests
